package/__init__.py
package/cmd/main.py
package/cmd/modify.py
package/cmd/read.py
package/cmd/root.py
package/compiler/__init__.py
package/compiler/compiler.py
package/compiler/task.py
package/hooks/__init__.py
package/hooks/task_logger.py
package/hooks/todo_process.py
package/hooks/utils.py
package/ir/__init__.py
package/ir/todo.py
package/provider/__init__.py
package/provider/todo/__init__.py
package/provider/todo/todo_ast.py
package/provider/todo/todo_regex.py
package/utils/__init__.py
package/utils/utils.py
task_flow_enmu-0.1.1.dist-info/METADATA
task_flow_enmu-0.1.1.dist-info/WHEEL
task_flow_enmu-0.1.1.dist-info/entry_points.txt
task_flow_enmu-0.1.1.dist-info/top_level.txt
task_flow_enmu-0.1.1.dist-info/RECORD
